[
  {
    "#commont": "id and name is item's, createAt is order's",
    "id": 1,
    "name": "test",
    "price":150,
    "createAt": 1468462316771,
    "status": 0
  },
  {
    "#commont": "id and name is item's, createAt is order's",
    "id": 2,
    "name": "test",
    "price":1500,
    "createAt": 1468462316771,
    "status": 1
  },
  {
    "#commont": "id and name is item's, createAt is order's",
    "id": 3,
    "name": "test",
    "price":1500,
    "createAt": 1468462316771,
    "status": 2
  },
  {
    "#commont": "id and name is item's, createAt is order's",
    "id": 4,
    "name": "test",
    "price":15000,
    "createAt": 1468462316771,
    "status": 3
  },
  {
    "#commont": "id and name is item's, createAt is order's",
    "id": 5,
    "name": "test",
    "price":15000,
    "createAt": 1468462316771,
    "status": 4
  },
  {
    "#commont": "id and name is item's, createAt is order's",
    "id": 6,
    "name": "test",
    "price":15000,
    "createAt": 1468462316771,
    "status": 5
  }
]

